Verilog/Codes/alu.v
module alu(S, A, B,  add_result, sub_result,bit5, sub_sign, and_result, GT, EQ, LT);
    input wire [3:0] A,B;
    input wire [1:0] S;
    output wire [3:0] add_result, sub_result, and_result;
    output wire bit5, sub_sign ;
    output wire GT, EQ, LT;
    wire [3:0] d;
    wire [1:0] s;
    wire f;

    not(s[0], S[0]);
    not(s[1], S[1]);

    and(d[0],s[1],s[0]); //00
    and(d[1],s[1],S[0]); //01
    and(d[2],S[1],s[0]); //10
    and(d[3],S[1],S[0]); //11
    and(f, d[0], d[1]);

    bit4_adder_subtractor Ares(.A(A),.B(B),.M(f),.s(add_result),.d(d[0]), .sign(bit5));
    bit4_adder_subtractor Sres(.A(A),.B(B),.M(d[1]),.s(sub_result),.d(d[1]), .sign(sub_sign));
    comparator comp(.A(A), .B(B), .d(d[2]), .gt(GT), .eq(EQ), .lt(LT));
    and_block Nres (.A(A), .B(B), .d(d[3]), .out(and_result));

endmodule

module enable_block(X,en,x);
    input wire [3:0] X;
    input wire en;
    output wire [3:0] x;

    and(x[0],X[0],en);
    and(x[1],X[1],en);
    and(x[2],X[2],en);
    and(x[3],X[3],en);

endmodule

module updateB(M,b,bu);
    input wire [3:0] b;
    input wire M;
    output wire [3:0]bu;

    xor(bu[0],b[0],M);
    xor(bu[1],b[1],M);
    xor(bu[2],b[2],M);
    xor(bu[3],b[3],M);

endmodule

module full_adder(x,y,c_in,s_0,c_out);
    output wire s_0, c_out;
    input wire x,y,c_in;

    wire o1, o2, o3;

    xor(o1,x,y);
    xor(s_0,o1,c_in);
    and(o2, c_in, o1);
    and(o3,x,y);
    or(c_out,o2,o3);

endmodule

module bit4_adder_subtractor(A,B,M,s,d,sign);
    input wire [3:0] A,B;
    input wire M,d;
    output wire [3:0] s;
    output wire sign;

    wire [3:0] c;
    wire [3:0] a,b,bu;
    
    enable_block forA(.X(A), .en(d), .x(a));
    enable_block forB(.X(B), .en(d), .x(b));
    
    updateB b_processed(.M(M),.b(b),.bu(bu));

    full_adder s0(.x(a[0]),.y(bu[0]),.c_in(M),.s_0(s[0]), .c_out(c[1]));
    full_adder s1(.x(a[1]),.y(bu[1]),.c_in(c[1]),.s_0(s[1]), .c_out(c[2]));
    full_adder s2(.x(a[2]),.y(bu[2]),.c_in(c[2]),.s_0(s[2]), .c_out(c[3]));
    full_adder s3(.x(a[3]),.y(bu[3]),.c_in(c[3]),.s_0(s[3]), .c_out(sign));

endmodule

module and_block(A,B,d,out);
    input wire [3:0] A,B;
    input wire d;
    output wire [3:0] out;

    wire [3:0] a,b;

    enable_block forA(.X(A), .en(d), .x(a));
    enable_block forB(.X(B), .en(d), .x(b));

    and(out[0],a[0],b[0]);
    and(out[1],a[1],b[1]);
    and(out[2],a[2],b[2]);
    and(out[3],a[3],b[3]);   

endmodule

module comparator(A,B,d,gt,eq,lt);
    input wire [3:0] A,B;
    input wire d;
    output wire gt,eq,lt;

    wire [3:0] a,b,e,g,l,bu,au;
    wire e0, e1 , eh;
    

    enable_block forA(.X(A), .en(d), .x(a));
    enable_block forB(.X(B), .en(d), .x(b));

    //equal check
    xnor(e[0],a[0],b[0]);
    xnor(e[1],a[1],b[1]);
    xnor(e[2],a[2],b[2]);
    xnor(e[3],a[3],b[3]);

    and(e0,e[3],e[2]);
    and(e1,e0,e[1]);
    and(eq,e1,e[0],d);
    

    //greater than

    updateB bp(.M(d),.b(b),.bu(bu));
    and(g[3],a[3],bu[3]);
    and(g[2],bu[2],a[2],e[3]);
    and(g[1],bu[1],a[1],e0);
    and(g[0],bu[0],a[0],e1);
    or(gt,g[3],g[2],g[1],g[0]);
    
    not(gc,gt);
    not(ec,eq);
    and(lt,ec, gc, d);

endmodule

Verilog/Codes/alu_tb.v
module alu_tb;
    reg [3:0] A, B;
    reg [1:0] S;
    wire [3:0] add_result, sub_result, and_result;
    wire bit5, sub_sign ;
    wire GT, EQ, LT;

    alu sunshine(
        .S(S), .A(A), .B(B),
        .add_result(add_result), .sub_result(sub_result),
        .bit5(bit5), .sub_sign(sub_sign),
        .and_result(and_result), .GT(GT), .EQ(EQ), .LT(LT)
    );

    initial begin 
        A = 4; B = 10; S = 2'b00;
        #5;
        A = 4'b1111; B = 4'b1101; S = 2'b01;
        #5;
        A = 4'b1010; B = 4'b0101; S = 2'b10;
        #5;
        A = 4'b1111; B = 4'b1111; S = 2'b10;
        #5;
        A = 4'b1111; B = 4'b1100; S = 2'b11;
        #5;
        A = 7; B = 1; S =2'b10;
        #5
        A = 13; B = 10; S = 2'b01;
        #5
        A = 2; B = 13; S = 0;
        #5
        $finish;
    end

    initial begin 
        $monitor("%t| A = %b| B = %b| S = %b| Sum = %b%b| Difference = %b%b| GT = %b, LT = %b, EQ= %b| And Result = %b", 
            $time, A, B, S, bit5, add_result, sub_sign, sub_result, GT, LT, EQ, and_result);
        $dumpfile("alu_tb_dump.vcd");
        $dumpvars(0, alu_tb);
    end

endmodule

Verilog/Codes/alu_tb_dump.vcd
$date
	Tue Nov  7 11:54:01 2023
$end
$version
	Icarus Verilog
$end
$timescale
	1s
$end
$scope module alu_tb $end
$var wire 1 ! sub_sign $end
$var wire 4 " sub_result [3:0] $end
$var wire 1 # bit5 $end
$var wire 4 $ and_result [3:0] $end
$var wire 4 % add_result [3:0] $end
$var wire 1 & LT $end
$var wire 1 ' GT $end
$var wire 1 ( EQ $end
$var reg 4 ) A [3:0] $end
$var reg 4 * B [3:0] $end
$var reg 2 + S [1:0] $end
$scope module sunshine $end
$var wire 4 , A [3:0] $end
$var wire 4 - B [3:0] $end
$var wire 2 . S [1:0] $end
$var wire 1 / f $end
$var wire 1 ! sub_sign $end
$var wire 4 0 sub_result [3:0] $end
$var wire 2 1 s [1:0] $end
$var wire 4 2 d [3:0] $end
$var wire 1 # bit5 $end
$var wire 4 3 and_result [3:0] $end
$var wire 4 4 add_result [3:0] $end
$var wire 1 & LT $end
$var wire 1 ' GT $end
$var wire 1 ( EQ $end
$scope module Ares $end
$var wire 4 5 A [3:0] $end
$var wire 4 6 B [3:0] $end
$var wire 1 / M $end
$var wire 1 7 d $end
$var wire 1 # sign $end
$var wire 4 8 s [3:0] $end
$var wire 4 9 c [3:0] $end
$var wire 4 : bu [3:0] $end
$var wire 4 ; b [3:0] $end
$var wire 4 < a [3:0] $end
$scope module b_processed $end
$var wire 1 / M $end
$var wire 4 = bu [3:0] $end
$var wire 4 > b [3:0] $end
$upscope $end
$scope module forA $end
$var wire 4 ? X [3:0] $end
$var wire 1 7 en $end
$var wire 4 @ x [3:0] $end
$upscope $end
$scope module forB $end
$var wire 4 A X [3:0] $end
$var wire 1 7 en $end
$var wire 4 B x [3:0] $end
$upscope $end
$scope module s0 $end
$var wire 1 / c_in $end
$var wire 1 C c_out $end
$var wire 1 D o1 $end
$var wire 1 E o2 $end
$var wire 1 F o3 $end
$var wire 1 G s_0 $end
$var wire 1 H x $end
$var wire 1 I y $end
$upscope $end
$scope module s1 $end
$var wire 1 J c_in $end
$var wire 1 K c_out $end
$var wire 1 L o1 $end
$var wire 1 M o2 $end
$var wire 1 N o3 $end
$var wire 1 O s_0 $end
$var wire 1 P x $end
$var wire 1 Q y $end
$upscope $end
$scope module s2 $end
$var wire 1 R c_in $end
$var wire 1 S c_out $end
$var wire 1 T o1 $end
$var wire 1 U o2 $end
$var wire 1 V o3 $end
$var wire 1 W s_0 $end
$var wire 1 X x $end
$var wire 1 Y y $end
$upscope $end
$scope module s3 $end
$var wire 1 Z c_in $end
$var wire 1 # c_out $end
$var wire 1 [ o1 $end
$var wire 1 \ o2 $end
$var wire 1 ] o3 $end
$var wire 1 ^ s_0 $end
$var wire 1 _ x $end
$var wire 1 ` y $end
$upscope $end
$upscope $end
$scope module Nres $end
$var wire 4 a A [3:0] $end
$var wire 4 b B [3:0] $end
$var wire 1 c d $end
$var wire 4 d out [3:0] $end
$var wire 4 e b [3:0] $end
$var wire 4 f a [3:0] $end
$scope module forA $end
$var wire 4 g X [3:0] $end
$var wire 1 c en $end
$var wire 4 h x [3:0] $end
$upscope $end
$scope module forB $end
$var wire 4 i X [3:0] $end
$var wire 1 c en $end
$var wire 4 j x [3:0] $end
$upscope $end
$upscope $end
$scope module Sres $end
$var wire 4 k A [3:0] $end
$var wire 4 l B [3:0] $end
$var wire 1 m M $end
$var wire 1 n d $end
$var wire 1 ! sign $end
$var wire 4 o s [3:0] $end
$var wire 4 p c [3:0] $end
$var wire 4 q bu [3:0] $end
$var wire 4 r b [3:0] $end
$var wire 4 s a [3:0] $end
$scope module b_processed $end
$var wire 1 m M $end
$var wire 4 t bu [3:0] $end
$var wire 4 u b [3:0] $end
$upscope $end
$scope module forA $end
$var wire 4 v X [3:0] $end
$var wire 1 n en $end
$var wire 4 w x [3:0] $end
$upscope $end
$scope module forB $end
$var wire 4 x X [3:0] $end
$var wire 1 n en $end
$var wire 4 y x [3:0] $end
$upscope $end
$scope module s0 $end
$var wire 1 m c_in $end
$var wire 1 z c_out $end
$var wire 1 { o1 $end
$var wire 1 | o2 $end
$var wire 1 } o3 $end
$var wire 1 ~ s_0 $end
$var wire 1 !" x $end
$var wire 1 "" y $end
$upscope $end
$scope module s1 $end
$var wire 1 #" c_in $end
$var wire 1 $" c_out $end
$var wire 1 %" o1 $end
$var wire 1 &" o2 $end
$var wire 1 '" o3 $end
$var wire 1 (" s_0 $end
$var wire 1 )" x $end
$var wire 1 *" y $end
$upscope $end
$scope module s2 $end
$var wire 1 +" c_in $end
$var wire 1 ," c_out $end
$var wire 1 -" o1 $end
$var wire 1 ." o2 $end
$var wire 1 /" o3 $end
$var wire 1 0" s_0 $end
$var wire 1 1" x $end
$var wire 1 2" y $end
$upscope $end
$scope module s3 $end
$var wire 1 3" c_in $end
$var wire 1 ! c_out $end
$var wire 1 4" o1 $end
$var wire 1 5" o2 $end
$var wire 1 6" o3 $end
$var wire 1 7" s_0 $end
$var wire 1 8" x $end
$var wire 1 9" y $end
$upscope $end
$upscope $end
$scope module comp $end
$var wire 4 :" A [3:0] $end
$var wire 4 ;" B [3:0] $end
$var wire 1 <" d $end
$var wire 1 =" e0 $end
$var wire 1 >" e1 $end
$var wire 1 ?" ec $end
$var wire 1 ( eq $end
$var wire 1 @" gc $end
$var wire 1 ' gt $end
$var wire 1 & lt $end
$var wire 4 A" g [3:0] $end
$var wire 4 B" e [3:0] $end
$var wire 4 C" bu [3:0] $end
$var wire 4 D" b [3:0] $end
$var wire 4 E" a [3:0] $end
$scope module bp $end
$var wire 1 <" M $end
$var wire 4 F" bu [3:0] $end
$var wire 4 G" b [3:0] $end
$upscope $end
$scope module forA $end
$var wire 4 H" X [3:0] $end
$var wire 1 <" en $end
$var wire 4 I" x [3:0] $end
$upscope $end
$scope module forB $end
$var wire 4 J" X [3:0] $end
$var wire 1 <" en $end
$var wire 4 K" x [3:0] $end
$upscope $end
$upscope $end
$upscope $end
$upscope $end
$enddefinitions $end
#0
$dumpvars
b0 K"
b1010 J"
b0 I"
b100 H"
b0 G"
b0 F"
b0 E"
b0 D"
b0 C"
b1111 B"
b0 A"
1@"
1?"
1>"
1="
0<"
b1010 ;"
b100 :"
09"
08"
07"
06"
05"
04"
03"
02"
01"
00"
0/"
0."
0-"
0,"
0+"
0*"
0)"
0("
0'"
0&"
0%"
0$"
0#"
0""
0!"
0~
0}
0|
0{
0z
b0 y
b1010 x
b0 w
b100 v
b0 u
b0 t
b0 s
b0 r
b0 q
b0z p
b0 o
0n
0m
b1010 l
b100 k
b0 j
b1010 i
b0 h
b100 g
b0 f
b0 e
b0 d
0c
b1010 b
b100 a
1`
0_
1^
0]
0\
1[
0Z
0Y
1X
1W
0V
0U
1T
0S
0R
1Q
0P
1O
0N
0M
1L
0K
0J
0I
0H
0G
0F
0E
0D
0C
b1010 B
b1010 A
b100 @
b100 ?
b1010 >
b1010 =
b100 <
b1010 ;
b1010 :
b0z 9
b1110 8
17
b1010 6
b100 5
b1110 4
b0 3
b1 2
b11 1
b0 0
0/
b0 .
b1010 -
b100 ,
b0 +
b1010 *
b100 )
0(
0'
0&
b1110 %
b0 $
0#
b0 "
0!
$end
#5
0W
07"
1("
1|
1."
15"
0G
0\
1#"
1+"
13"
1{
1-"
14"
0Z
0X
1z
1$"
b111z p
1,"
1!
0M
0S
0J
0`
0}
1'"
0/"
06"
0F
0T
0V
0C
0R
07
0""
1*"
02"
09"
1!"
1)"
11"
18"
0I
0Q
0Y
0E
0O
b0z 9
0K
b0 %
b0 4
b0 8
0^
0#
0/
b10 q
b10 t
b10 "
b10 0
b10 o
0~
b1111 s
b1111 w
b1101 r
b1101 u
b1101 y
b0 :
b0 =
0D
0L
0N
0[
0]
1m
1n
0H
0P
0_
b10 1
b10 2
b0 ;
b0 >
b0 B
b0 <
b0 @
b1 +
b1 .
b1101 *
b1101 -
b1101 6
b1101 A
b1101 b
b1101 i
b1101 l
b1101 x
b1101 ;"
b1101 J"
b1111 )
b1111 ,
b1111 5
b1111 ?
b1111 a
b1111 g
b1111 k
b1111 v
b1111 :"
b1111 H"
#10
0@"
0>"
1'
0="
07"
b1000 A"
b0 B"
0+"
0!
1?"
0~
0("
0$"
05"
03"
0(
0&
b1010 C"
b1010 F"
b1010 E"
b1010 I"
b101 D"
b101 G"
b101 K"
0#"
0'"
04"
0,"
1<"
0""
0*"
02"
b0z p
0z
0)"
08"
b0 "
b0 0
b0 o
00"
0."
b0 q
b0 t
0|
0{
0-"
0m
0n
0!"
01"
b1 1
b100 2
b0 r
b0 u
b0 y
b0 s
b0 w
b10 +
b10 .
b101 *
b101 -
b101 6
b101 A
b101 b
b101 i
b101 l
b101 x
b101 ;"
b101 J"
b1010 )
b1010 ,
b1010 5
b1010 ?
b1010 a
b1010 g
b1010 k
b1010 v
b1010 :"
b1010 H"
#15
1@"
0?"
0'
1(
1>"
b0 A"
1="
b0 C"
b0 F"
b1111 B"
b1111 D"
b1111 G"
b1111 K"
b1111 E"
b1111 I"
b1111 *
b1111 -
b1111 6
b1111 A
b1111 b
b1111 i
b1111 l
b1111 x
b1111 ;"
b1111 J"
b1111 )
b1111 ,
b1111 5
b1111 ?
b1111 a
b1111 g
b1111 k
b1111 v
b1111 :"
b1111 H"
#20
1@"
0'
1?"
b0 E"
b0 I"
b1100 $
b1100 3
b1100 d
0(
b0 A"
1>"
0<"
b1111 f
b1111 h
b1100 e
b1100 j
b0 C"
b0 F"
b1111 B"
1c
b0 1
b1000 2
b0 D"
b0 G"
b0 K"
b11 +
b11 .
b1100 *
b1100 -
b1100 6
b1100 A
b1100 b
b1100 i
b1100 l
b1100 x
b1100 ;"
b1100 J"
#25
0@"
0>"
1'
0="
b100 A"
b1001 B"
1?"
0(
0&
b1110 C"
b1110 F"
b111 E"
b111 I"
b1 D"
b1 G"
b1 K"
1<"
b0 $
b0 3
b0 d
0c
b1 1
b100 2
b0 e
b0 j
b0 f
b0 h
b10 +
b10 .
b1 *
b1 -
b1 6
b1 A
b1 b
b1 i
b1 l
b1 x
b1 ;"
b1 J"
b111 )
b111 ,
b111 5
b111 ?
b111 a
b111 g
b111 k
b111 v
b111 :"
b111 H"
#30
15"
1#"
13"
14"
1("
1z
b101z p
1,"
1!
1>"
1@"
0%"
1}
1/"
06"
1="
0'
1""
0*"
12"
09"
1!"
11"
18"
b101 q
b101 t
b11 "
b11 0
b11 o
1~
b1101 s
b1101 w
b1010 r
b1010 u
b1010 y
1m
1n
b0 C"
b0 F"
b1111 B"
b0 A"
0<"
b10 1
b10 2
b0 D"
b0 G"
b0 K"
b0 E"
b0 I"
b1 +
b1 .
b1010 *
b1010 -
b1010 6
b1010 A
b1010 b
b1010 i
b1010 l
b1010 x
b1010 ;"
b1010 J"
b1101 )
b1101 ,
b1101 5
b1101 ?
b1101 a
b1101 g
b1101 k
b1101 v
b1101 :"
b1101 H"
#35
1G
1W
1^
1D
1T
1[
b1111 %
b1111 4
b1111 8
1O
1I
1Y
1`
0~
1L
b1101 :
b1101 =
0."
1P
0""
02"
0+"
b10 <
b10 @
b1101 ;
b1101 >
b1101 B
0#"
0$"
03"
0!
17
09"
0z
0("
0&"
00"
b0z p
0,"
b0 "
b0 0
b0 o
07"
05"
b0 q
b0 t
0{
0}
0%"
0-"
0/"
04"
0m
0n
0!"
0)"
01"
08"
b11 1
b1 2
b0 r
b0 u
b0 y
b0 s
b0 w
b0 +
b0 .
b1101 *
b1101 -
b1101 6
b1101 A
b1101 b
b1101 i
b1101 l
b1101 x
b1101 ;"
b1101 J"
b10 )
b10 ,
b10 5
b10 ?
b10 a
b10 g
b10 k
b10 v
b10 :"
b10 H"
